odin/__init__.py
odin/api_client.py
odin/configuration.py
odin/rest.py
odin/models/__init__.py
odin/models/api_response.py
odin/models/cert_count.py
odin/models/certificate_api_response.py
odin/models/certificate_cert_count.py
odin/models/certificate_cert_count_request.py
odin/models/certificate_cert_scroll.py
odin/models/certificate_cert_scroll_request.py
odin/models/certificate_cert_search_request.py
odin/models/certificate_cert_summary_request.py
odin/models/certificate_certificate_hash_response.py
odin/models/certificate_certificate_hash_response_data.py
odin/models/certificate_certificate_hash_response_data_certificate.py
odin/models/certificate_certificate_hash_response_data_certificate_extensions.py
odin/models/certificate_certificate_hash_response_data_certificate_extensions_authority_info_access.py
odin/models/certificate_certificate_hash_response_data_certificate_extensions_basic_constraints.py
odin/models/certificate_certificate_hash_response_data_certificate_extensions_certificate_policies.py
odin/models/certificate_certificate_hash_response_data_certificate_extensions_extended_key_usage.py
odin/models/certificate_certificate_hash_response_data_certificate_extensions_key_usage.py
odin/models/certificate_certificate_hash_response_data_certificate_extensions_subject_alt_name.py
odin/models/certificate_certificate_hash_response_data_certificate_issuer.py
odin/models/certificate_certificate_hash_response_data_certificate_signature.py
odin/models/certificate_certificate_hash_response_data_certificate_signature_signature_algorithm.py
odin/models/certificate_certificate_hash_response_data_certificate_subject.py
odin/models/certificate_certificate_hash_response_data_certificate_subject_alt_name.py
odin/models/certificate_certificate_hash_response_data_certificate_subject_alt_name_extended_dns_names.py
odin/models/certificate_certificate_hash_response_data_certificate_subject_key_info.py
odin_sdk-2.0.1.dist-info/METADATA
odin_sdk-2.0.1.dist-info/WHEEL
odin_sdk-2.0.1.dist-info/top_level.txt
odin_sdk-2.0.1.dist-info/RECORD
