Metadata-Version: 2.1
Name: odin-sdk
Version: 2.0.1
Summary: Odin SDK provides a way to search across various services related to cybersecurity, IP services, certificates, exposed files and more
Home-page: https://odin.io
Author-email: cyble <team@cyble.com>
Project-URL: Homepage, https://github.com/cybledev/odin-sdk-python
Requires-Python: >=3.7
Requires-Dist: certifi>=14.05.14
Requires-Dist: six>=1.10
Requires-Dist: python-dateutil>=2.5.3
Requires-Dist: setuptools>=21.0.0
Requires-Dist: urllib3>=1.15.1
